{
  "doctype": "Workspace",
  "name": "SFA Core",
  "label": "SFA Core",
  "title": "SFA Core",
  "icon": "target",
  "module": "SFA Core",
  "is_standard": 1,
  "public": 1,
  "for_user": "",
  "sequence_id": 99,
  "shortcuts": [
    {"type": "DocType", "label": "Beat Plans", "link_to": "SFA Beat Plan", "color": "#D97706"},
    {"type": "DocType", "label": "SFA Payments", "link_to": "SFA Payment", "color": "#E11D48"},
    {"type": "DocType", "label": "SFA Visits", "link_to": "SFA Visit", "color": "#2563EB"},
    {"type": "DocType", "label": "Form Templates", "link_to": "SFA Form Template", "color": "#7C3AED"}
  ],
  "links": [
    {"type": "Card Break", "label": "Field Operations", "is_query_report": 0},
    {"type": "Link", "label": "SFA Visit", "link_type": "DocType", "link_to": "SFA Visit", "is_query_report": 0},
    {"type": "Link", "label": "SFA Beat Plan", "link_type": "DocType", "link_to": "SFA Beat Plan", "is_query_report": 0},
    {"type": "Link", "label": "SFA Payment", "link_type": "DocType", "link_to": "SFA Payment", "is_query_report": 0},
    {"type": "Link", "label": "SFA Field Activity", "link_type": "DocType", "link_to": "SFA Field Activity", "is_query_report": 0},
    {"type": "Card Break", "label": "Customers", "is_query_report": 0},
    {"type": "Link", "label": "Customer", "link_type": "DocType", "link_to": "Customer", "is_query_report": 0},
    {"type": "Link", "label": "SFA Saved Location", "link_type": "DocType", "link_to": "SFA Saved Location", "is_query_report": 0},
    {"type": "Card Break", "label": "Forms", "is_query_report": 0},
    {"type": "Link", "label": "SFA Form Template", "link_type": "DocType", "link_to": "SFA Form Template", "is_query_report": 0},
    {"type": "Link", "label": "SFA Form Response", "link_type": "DocType", "link_to": "SFA Form Response", "is_query_report": 0},
    {"type": "Card Break", "label": "Gamification", "is_query_report": 0},
    {"type": "Link", "label": "SFA Points Config", "link_type": "DocType", "link_to": "SFA Points Config", "is_query_report": 0},
    {"type": "Link", "label": "SFA Badge", "link_type": "DocType", "link_to": "SFA Badge", "is_query_report": 0},
    {"type": "Link", "label": "SFA Rep Points Ledger", "link_type": "DocType", "link_to": "SFA Rep Points Ledger", "is_query_report": 0},
    {"type": "Card Break", "label": "Settings", "is_query_report": 0},
    {"type": "Link", "label": "SFA Target Period", "link_type": "DocType", "link_to": "SFA Target Period", "is_query_report": 0},
    {"type": "Link", "label": "SFA SKU Points Multiplier", "link_type": "DocType", "link_to": "SFA SKU Points Multiplier", "is_query_report": 0}
  ]
}
